README.rst
setup.cfg
setup.py
Louie-latest.egg-info/PKG-INFO
Louie-latest.egg-info/SOURCES.txt
Louie-latest.egg-info/dependency_links.txt
Louie-latest.egg-info/not-zip-safe
Louie-latest.egg-info/requires.txt
Louie-latest.egg-info/top_level.txt
louie/__init__.py
louie/dispatcher.py
louie/error.py
louie/plugin.py
louie/robustapply.py
louie/saferef.py
louie/sender.py
louie/signal.py
louie/version.py
louie/test/__init__.py
louie/test/conftest.py
louie/test/fixture.py
louie/test/test_dispatcher.py
louie/test/test_plugin.py
louie/test/test_robustapply.py
louie/test/test_saferef.py