Metadata-Version: 1.1
Name: Louie-latest
Version: 1.3.1
Summary: Signal dispatching mechanism
Home-page: https://github.com/11craft/louie/
Author: Patrick K. O'Brien and contributors
Author-email: UNKNOWN
License: BSD
Download-URL: https://pypi.python.org/pypi/Louie
Platform: UNKNOWN
Classifier: Intended Audience :: Developers
Classifier: License :: OSI Approved :: BSD License
Classifier: Programming Language :: Python
Classifier: Topic :: Software Development :: Libraries :: Python Modules
